{
  "version": "1.0",
  "last_updated": "2026-02-16T17:26:44.540771+00:00",
  "issues": {
    "11": {
      "lld_path": "docs\\lld\\active\\LLD-011.md",
      "status": "approved",
      "has_gemini_review": true,
      "final_verdict": "APPROVED",
      "last_review_date": "2026-02-16T17:14:42.040426+00:00",
      "review_count": 2
    },
    "5": {
      "lld_path": "docs\\lld\\active\\LLD-005.md",
      "status": "approved",
      "has_gemini_review": true,
      "final_verdict": "APPROVED",
      "last_review_date": "2026-02-16T17:20:47.805396+00:00",
      "review_count": 1
    },
    "9": {
      "lld_path": "docs\\lld\\active\\LLD-009.md",
      "status": "approved",
      "has_gemini_review": true,
      "final_verdict": "APPROVED",
      "last_review_date": "2026-02-16T17:26:44.532641+00:00",
      "review_count": 1
    }
  }
}
